mci_model/VERSION
mci_model/__init__.py
mci_model/config.yml
mci_model/pipeline.py
mci_model/predict.py
mci_model/train_pipeline.py
mci_model/config/__init__.py
mci_model/config/base.py
mci_model/datasets/test.csv
mci_model/datasets/train.csv
mci_model/fitted_models/mci_model_output_v0.0.38.pkl
mci_model/utilities/__init__.py
mci_model/utilities/data_manager.py
mci_model/utilities/transformers.py
mci_model/utilities/transformers_old.py
mci_model/utilities/validation.py
MCI_Crime_Location_Prediction_Model-0.0.38.dist-info/LICENSE.txt
MCI_Crime_Location_Prediction_Model-0.0.38.dist-info/METADATA
MCI_Crime_Location_Prediction_Model-0.0.38.dist-info/WHEEL
MCI_Crime_Location_Prediction_Model-0.0.38.dist-info/top_level.txt
MCI_Crime_Location_Prediction_Model-0.0.38.dist-info/RECORD
